thermite/__init__.py
thermite/callbacks.py
thermite/cli_args_splitter.py
thermite/command.py
thermite/config.py
thermite/exceptions.py
thermite/preprocessing.py
thermite/preset_config.py
thermite/rich.py
thermite/run.py
thermite/signatures.py
thermite/type_converters.py
thermite/utils.py
thermite/parameters/__init__.py
thermite/parameters/base.py
thermite/parameters/create.py
thermite/parameters/group.py
thermite/parameters/processors.py
thermite/plugins/default_defs.py
thermite/plugins/help.py
thermite-0.1.1.dist-info/LICENSE
thermite-0.1.1.dist-info/WHEEL
thermite-0.1.1.dist-info/METADATA
thermite-0.1.1.dist-info/RECORD
