Metadata-Version: 2.1
Name: thermite
Version: 0.1.1
Summary: A package for easily creating CLIs.
Author-email: Holger Hoefling <hhoeflin@gmail.com>
Requires-Python: >=3.10
Classifier: License :: OSI Approved :: MIT License
Requires-Dist: rich
Requires-Dist: more_itertools
Requires-Dist: attrs
Requires-Dist: cattrs
Requires-Dist: beartype
Requires-Dist: docstring-parser
Requires-Dist: immutabledict
Requires-Dist: rich
Requires-Dist: exceptiongroup
Requires-Dist: prettyprinter
Requires-Dist: loguru
Requires-Dist: pudb >=2021.2.2 ; extra == "dev"
Requires-Dist: pytest >=6.2.5 ; extra == "dev"
Requires-Dist: pytest-pudb >=0.7.0 ; extra == "dev"
Requires-Dist: mypy ; extra == "dev"
Requires-Dist: black ; extra == "dev"
Requires-Dist: Flake8-pyproject ; extra == "dev"
Requires-Dist: pydocstyle ; extra == "dev"
Requires-Dist: mkdocs-material ; extra == "dev"
Requires-Dist: mkdocstrings[python] ; extra == "dev"
Provides-Extra: dev
